gofra/__init__.py
gofra/__main__.py
gofra/_distlib/ext/libc.gof
gofra/_distlib/ext/raylib.gof
gofra/_distlib/lib/ext/libc.gof
gofra/_distlib/lib/ext/raylib.gof
gofra/_distlib/lib/os/general.gof
gofra/_distlib/lib/os/os.gof
gofra/_distlib/lib/os/socket.gof
gofra/_distlib/lib/os/syscall.gof
gofra/_distlib/lib/std.gof
gofra/_distlib/lib/types.gof
gofra/_distlib/os/general.gof
gofra/_distlib/os/os.gof
gofra/_distlib/os/socket.gof
gofra/_distlib/os/syscall.gof
gofra/_distlib/std.gof
gofra/_distlib/types.gof
gofra/assembler/__init__.py
gofra/assembler/assembler.py
gofra/assembler/exceptions.py
gofra/cli/__init__.py
gofra/cli/arguments.py
gofra/cli/entry_point.py
gofra/cli/errors.py
gofra/cli/ir.py
gofra/cli/output.py
gofra/codegen/__init__.py
gofra/codegen/backends/__init__.py
gofra/codegen/backends/aarch64_macos/__init__.py
gofra/codegen/backends/aarch64_macos/_context.py
gofra/codegen/backends/aarch64_macos/assembly.py
gofra/codegen/backends/aarch64_macos/codegen.py
gofra/codegen/backends/aarch64_macos/registers.py
gofra/codegen/backends/amd64_linux/__init__.py
gofra/codegen/backends/amd64_linux/_context.py
gofra/codegen/backends/amd64_linux/assembly.py
gofra/codegen/backends/amd64_linux/codegen.py
gofra/codegen/backends/amd64_linux/registers.py
gofra/codegen/backends/base.py
gofra/codegen/backends/general.py
gofra/codegen/exceptions.py
gofra/codegen/generator.py
gofra/codegen/get_backend.py
gofra/codegen/targets.py
gofra/consts.py
gofra/context.py
gofra/exceptions.py
gofra/gofra.py
gofra/lexer/__init__.py
gofra/lexer/_state.py
gofra/lexer/exceptions.py
gofra/lexer/helpers.py
gofra/lexer/io/__init__.py
gofra/lexer/io/exceptions.py
gofra/lexer/io/io.py
gofra/lexer/keywords.py
gofra/lexer/lexer.py
gofra/lexer/tokens.py
gofra/optimizer/__init__.py
gofra/optimizer/optimizer.py
gofra/optimizer/strategies/__init__.py
gofra/optimizer/strategies/constant_folding.py
gofra/optimizer/strategies/dead_code_elimination.py
gofra/parser/__init__.py
gofra/parser/_context.py
gofra-0.0.5.dist-info/LICENSE
gofra-0.0.5.dist-info/METADATA
gofra-0.0.5.dist-info/WHEEL
gofra-0.0.5.dist-info/entry_points.txt
gofra-0.0.5.dist-info/RECORD
