Metadata-Version: 2.3
Name: gofra
Version: 0.0.5
Summary: A Stack-based compiled programming language
License: MIT
Keywords: compiler,language
Author: Kirill Zhosul
Author-email: kirillzhosul@yandex.com
Requires-Python: >=3.12,<4.0
Classifier: License :: OSI Approved :: MIT License
Classifier: Programming Language :: Python :: 3
Classifier: Programming Language :: Python :: 3.12
Classifier: Programming Language :: Python :: 3.13
Project-URL: Documentation, https://kirillzhosul.github.io/gofra
